LICENSE
README.rst
setup.py
tictactoe_gpt_finetuning/__init__.py
tictactoe_gpt_finetuning/finetune.py
tictactoe_gpt_finetuning/model.py
tictactoe_gpt_finetuning/tictactoe.py
tictactoe_gpt_finetuning.egg-info/PKG-INFO
tictactoe_gpt_finetuning.egg-info/SOURCES.txt
tictactoe_gpt_finetuning.egg-info/dependency_links.txt
tictactoe_gpt_finetuning.egg-info/requires.txt
tictactoe_gpt_finetuning.egg-info/top_level.txt