Metadata-Version: 2.1
Name: tictactoe-gpt-finetuning
Version: 0.1.3
Summary: Python tic tac toe state generator and GPT fine tuning
Home-page: https://github.com/pesvut/tictactoe-gpt-finetuning
Author: Nicky Pochinkov
Author-email: work@nicky.pro
License: MIT
Keywords: tictactoe,llm,language-models
License-File: LICENSE
